vin_decoder_nhtsa/__init__.py
vin_decoder_nhtsa/decoder.py
vin_decoder_nhtsa-0.0.2.dist-info/METADATA
vin_decoder_nhtsa-0.0.2.dist-info/WHEEL
vin_decoder_nhtsa-0.0.2.dist-info/licenses/LICENSE
vin_decoder_nhtsa-0.0.2.dist-info/RECORD
