Metadata-Version: 2.1
Name: vin_decoder_nhtsa
Version: 0.0.2
Summary: Python module for decoding VIN metadata from NHTSA API
Project-URL: Homepage, https://github.com/conrey-engineering/python_vin_decoder_nhtsa
Project-URL: Bug Tracker, https://github.com/conrey-engineering/python_vin_decoder_nhtsa/issues
Author-email: Alex Conrey <alex@conrey.engineering>
License-File: LICENSE
Classifier: License :: OSI Approved :: MIT License
Classifier: Operating System :: OS Independent
Classifier: Programming Language :: Python :: 3
Requires-Python: >=3.7
